<?xml version="1.0" encoding="utf-8"?>
<RuleSetDef xmlns:xsi="http://www.w3.org/2001/XMLSchema-instance" xmlns:xsd="http://www.w3.org/2001/XMLSchema"
  Revision="1"
  PublicRevision="1"
  Guid="077b0aad-d232-4422-b9c0-ec3ee148144a"
  Name="InActiveRuleSet">
  <DefaultActivation xmlns="http://www.inrule.com/XmlSchema/Schema">false</DefaultActivation>
  <FireMode xmlns="http://www.inrule.com/XmlSchema/Schema">Auto</FireMode>
  <RunMode xmlns="http://www.inrule.com/XmlSchema/Schema">SequentialRunOnce</RunMode>
  <Rules xmlns="http://www.inrule.com/XmlSchema/Schema" />
  <HasContextVersionSettings xmlns="http://www.inrule.com/XmlSchema/Schema">false</HasContextVersionSettings>
</RuleSetDef>